{
    "wallpaper": "/home/lucas/.config/wpg/wallpapers/35.6541693_139.7022296.fframe_png",
    "alpha": "100",

    "special": {
        "background": "#09130D",
        "foreground": "#fef8e4",
        "cursor": "#fef8e4"
    },
    "colors": {
        "color0": "#09130D",
        "color1": "#605E30",
        "color2": "#2C4833",
        "color3": "#525F55",
        "color4": "#213251",
        "color5": "#314F51",
        "color6": "#6F7879",
        "color7": "#bfbbac",
        "color8": "#183524",
        "color9": "#868235",
        "color10": "#31653e",
        "color11": "#5f8668",
        "color12": "#233e70",
        "color13": "#376e71",
        "color14": "#81a7ac",
        "color15": "#fef8e4"
    }
}
